arcade_clickhouse/__init__.py
arcade_clickhouse/database_engine.py
arcade_clickhouse/tools/__init__.py
arcade_clickhouse/tools/clickhouse.py
arcade_clickhouse-0.1.1.dist-info/METADATA
arcade_clickhouse-0.1.1.dist-info/WHEEL
arcade_clickhouse-0.1.1.dist-info/RECORD
