Metadata-Version: 2.4
Name: arcade_clickhouse
Version: 0.1.1
Summary: Tools to query and explore a ClickHouse database
Author-email: evantahler <support@arcade.dev>
Requires-Python: >=3.10
Requires-Dist: aiochsa>=0.1.0
Requires-Dist: arcade-tdk<4.0.0,>=3.0.0
Requires-Dist: clickhouse-connect>=0.7.0
Requires-Dist: clickhouse-sqlalchemy>=0.2.0
Requires-Dist: greenlet>=3.2.3
Requires-Dist: pydantic>=2.11.7
Requires-Dist: setuptools>=80.9.0
Requires-Dist: sqlalchemy>=2.0.41
Provides-Extra: dev
Requires-Dist: arcade-mcp[all]<2.0.0,>=1.2.0; extra == 'dev'
Requires-Dist: arcade-serve<4.0.0,>=3.0.0; extra == 'dev'
Requires-Dist: mypy<1.6.0,>=1.5.1; extra == 'dev'
Requires-Dist: pre-commit<3.5.0,>=3.4.0; extra == 'dev'
Requires-Dist: pytest-asyncio<0.25.0,>=0.24.0; extra == 'dev'
Requires-Dist: pytest-cov<4.1.0,>=4.0.0; extra == 'dev'
Requires-Dist: pytest-mock<3.12.0,>=3.11.1; extra == 'dev'
Requires-Dist: pytest<8.4.0,>=8.3.0; extra == 'dev'
Requires-Dist: ruff<0.8.0,>=0.7.4; extra == 'dev'
Requires-Dist: tox<4.12.0,>=4.11.1; extra == 'dev'
